langchain_databricks/__init__.py
langchain_databricks/chat_models.py
langchain_databricks/embeddings.py
langchain_databricks/py.typed
langchain_databricks/utils.py
langchain_databricks/vectorstores.py
langchain_databricks-0.1.1.dist-info/LICENSE
langchain_databricks-0.1.1.dist-info/METADATA
langchain_databricks-0.1.1.dist-info/WHEEL
langchain_databricks-0.1.1.dist-info/RECORD
