Metadata-Version: 2.1
Name: langchain-databricks
Version: 0.1.1
Summary: An integration package connecting Databricks and LangChain
Home-page: https://github.com/langchain-ai/langchain-databricks
License: MIT
Requires-Python: >=3.9,<4.0
Classifier: License :: OSI Approved :: MIT License
Classifier: Programming Language :: Python :: 3
Classifier: Programming Language :: Python :: 3.9
Classifier: Programming Language :: Python :: 3.10
Classifier: Programming Language :: Python :: 3.11
Classifier: Programming Language :: Python :: 3.12
Requires-Dist: databricks-vectorsearch (>=0.40,<0.41)
Requires-Dist: langchain-core (>=0.2.35,<0.4)
Requires-Dist: mlflow (>=2.16.0) ; python_version >= "3.12"
Requires-Dist: mlflow (>=2.9) ; python_version < "3.12"
Requires-Dist: numpy (>=1.24.0) ; python_version < "3.12"
Requires-Dist: numpy (>=1.26.0) ; python_version >= "3.12"
Requires-Dist: scipy (<2) ; python_version < "3.12"
Requires-Dist: scipy (>=1.11) ; python_version >= "3.12"
Project-URL: Repository, https://github.com/langchain-ai/langchain-databricks
Project-URL: Release Notes, https://github.com/langchain-ai/langchain-databricks/releases
Project-URL: Source Code, https://github.com/langchain-ai/langchain-databricks/tree/main/libs/databricks
